curllm-1.0.40.data/scripts/curllm
curllm-1.0.40.dist-info/licenses/LICENSE
curllm_core/__init__.py
curllm_core/actions.py
curllm_core/agent_factory.py
curllm_core/atomic_functions.py
curllm_core/bql_extraction_orchestrator.py
curllm_core/bql_utils.py
curllm_core/browser_setup.py
curllm_core/browserless.py
curllm_core/captcha.py
curllm_core/captcha_slider.py
curllm_core/captcha_widget.py
curllm_core/cli_orchestrator.py
curllm_core/command_parser.py
curllm_core/config.py
curllm_core/config_logger.py
curllm_core/context_optimizer.py
curllm_core/diagnostics.py
curllm_core/dom_helpers.py
curllm_core/dom_statistics.py
curllm_core/dom_utils.py
curllm_core/dynamic_container_detector.py
curllm_core/dynamic_detector.py
curllm_core/error_handler.py
curllm_core/executor.py
curllm_core/extraction.py
curllm_core/feedback.py
curllm_core/form_fill.py
curllm_core/goal_detector_llm.py
curllm_core/headers.py
curllm_core/hierarchical_planner.py
curllm_core/human_verify.py
curllm_core/instruction_parser.py
curllm_core/intent_detector.py
curllm_core/iterative_extractor.py
curllm_core/llm.py
curllm_core/llm_config.py
curllm_core/llm_container_validator.py
curllm_core/llm_element_finder.py
curllm_core/llm_factory.py
curllm_core/llm_field_filler.py
curllm_core/llm_filter_validator.py
curllm_core/llm_guided_extractor.py
curllm_core/llm_heuristics.py
curllm_core/llm_planner.py
curllm_core/logger.py
curllm_core/metrics.py
curllm_core/multi_criteria_filter.py
curllm_core/navigation.py
curllm_core/orchestrator.py
curllm_core/orchestrator_steps.py
curllm_core/page_context.py
curllm_core/page_utils.py
curllm_core/planner_progress.py
curllm_core/product_extract.py
curllm_core/progressive_context.py
curllm_core/proxy.py
curllm_core/rate_limiter.py
curllm_core/remediation.py
curllm_core/rerun_cmd.py
curllm_core/result_corrector.py
curllm_core/result_evaluator.py
curllm_core/result_store.py
curllm_core/result_validator.py
curllm_core/retry.py
curllm_core/runtime.py
curllm_core/screenshots.py
curllm_core/semantic_query.py
curllm-1.0.40.dist-info/METADATA
curllm-1.0.40.dist-info/WHEEL
curllm-1.0.40.dist-info/entry_points.txt
curllm-1.0.40.dist-info/top_level.txt
curllm-1.0.40.dist-info/RECORD
