Metadata-Version: 2.4
Name: curllm
Version: 1.0.40
Summary: Browser Automation with Local LLM (8GB GPU compatible)
Author: Tom Sapletta
License-Expression: Apache-2.0
Project-URL: Homepage, https://github.com/wronai/curllm
Project-URL: Issues, https://github.com/wronai/curllm/issues
Keywords: llm,browser,automation,scraping,ollama,playwright
Classifier: Programming Language :: Python :: 3
Classifier: Programming Language :: Python :: 3 :: Only
Classifier: Operating System :: POSIX :: Linux
Classifier: Framework :: Flask
Classifier: Topic :: Internet :: WWW/HTTP
Requires-Python: >=3.10
License-File: LICENSE
Requires-Dist: flask
Requires-Dist: flask-cors
Requires-Dist: aiohttp
Requires-Dist: playwright
Requires-Dist: langchain-ollama
Requires-Dist: litellm>=1.0.0
Requires-Dist: pillow
Requires-Dist: opencv-python
Requires-Dist: pytesseract
Requires-Dist: numpy
Requires-Dist: websockets
Requires-Dist: requests
Requires-Dist: python-dotenv
Requires-Dist: psutil
Requires-Dist: pyyaml
Dynamic: license-file
